MCMAlgorithms/__init__.py
MCMAlgorithms/Classification/__init__.py
MCMAlgorithms/Evaluation/Relationship.py
MCMAlgorithms/Evaluation/Weighting.py
MCMAlgorithms/Evaluation/__init__.py
MCMAlgorithms/Mining/BasicAssociationRule.py
MCMAlgorithms/Mining/__init__.py
MCMAlgorithms/Optimization/Animals.py
MCMAlgorithms/Optimization/Evolution.py
MCMAlgorithms/Optimization/Single.py
MCMAlgorithms/Optimization/__init__.py
MCMAlgorithms/Regression/Simple.py
MCMAlgorithms/Regression/TimeSeries.py
MCMAlgorithms/Regression/__init__.py
MCMAlgorithms/Utility/Regression.py
MCMAlgorithms/Utility/__init__.py
MCMAlgorithms-0.0.5.dist-info/LICENSE.txt
MCMAlgorithms-0.0.5.dist-info/METADATA
MCMAlgorithms-0.0.5.dist-info/WHEEL
MCMAlgorithms-0.0.5.dist-info/entry_points.txt
MCMAlgorithms-0.0.5.dist-info/top_level.txt
MCMAlgorithms-0.0.5.dist-info/RECORD
